{

  "Select Itoms":{ 
        "name":"",
        "HSN_Code":"",
        "Description": "",
        "cost":""
      } ,

    "LiquidSoup":{ 
        "name":"Liquid_Soup",
        "HSN_Code":"L1",
        "Description": "use the Dishwash",
        "cost":"90"
      } ,
      
      "ToiletCleanner":{ 
        "name":"Toilet Cleanner",
        "HSN_Code":"L3",
        "Description": "Harpic",
        "cost":"200"
      },

      "Handwash":{ 
        "name":"Handwash",
        "HSN_Code":"L6",
        "Description": "Regular Use Handwash",
        "cost":"350"
      }

}